foyou_cli/__init__.py
foyou_cli/__main__.py
foyou_cli/aliyundrive.py
foyou_cli/ebook.py
foyou_cli/utils.py
foyou_cli/geoip/__init__.py
foyou_cli/geoip/geoip_pb2.py
foyou_cli/wikihow/__init__.py
foyou_cli/wikihow/script.js
foyou_cli/wikihow/style.css
foyou_cli-0.0.23.dist-info/LICENSE
foyou_cli-0.0.23.dist-info/METADATA
foyou_cli-0.0.23.dist-info/WHEEL
foyou_cli-0.0.23.dist-info/entry_points.txt
foyou_cli-0.0.23.dist-info/top_level.txt
foyou_cli-0.0.23.dist-info/RECORD
