Metadata-Version: 2.1
Name: foyou-cli
Version: 0.0.23
Summary: python package foyou-cli
Author: foyoux
Project-URL: Source, https://github.com/foyoux/foyou-cli
Project-URL: Homepage, https://github.com/foyoux/foyou-cli
Project-URL: Bug Tracker, https://github.com/foyoux/foyou-cli/issues
Keywords: foyou-cli
Classifier: Programming Language :: Python
Classifier: Programming Language :: Python :: 3
Classifier: Programming Language :: Python :: 3.7
Classifier: Programming Language :: Python :: 3.8
Classifier: Programming Language :: Python :: 3.9
Classifier: Programming Language :: Python :: 3.10
Classifier: Programming Language :: Python :: 3.11
Requires-Python: >=3.7
License-File: LICENSE
Requires-Dist: fire >=0.5.0
Requires-Dist: ebooklib >=0.18
Requires-Dist: psutil >=5.9.5
Requires-Dist: aligo >=6.2.3
Requires-Dist: lxml >=4.9.3
Requires-Dist: protobuf >=4.24.4
